benker/__init__.py
benker/alphabet.py
benker/box.py
benker/cell.py
benker/coord.py
benker/drawing.py
benker/grid.py
benker/size.py
benker/styled.py
benker/table.py
benker/units.py
benker/builders/__init__.py
benker/builders/base_builder.py
benker/builders/cals.py
benker/builders/formex.py
benker/builders/namespace.py
benker/common/__init__.py
benker/common/lxml_iterwalk.py
benker/common/lxml_qname.py
benker/converters/__init__.py
benker/converters/base_converter.py
benker/converters/cals2formex.py
benker/converters/formex2cals.py
benker/converters/ooxml2cals.py
benker/converters/ooxml2formex.py
benker/parsers/__init__.py
benker/parsers/base_parser.py
benker/parsers/formex.py
benker/parsers/cals/__init__.py
benker/parsers/cals/frame_styles.py
benker/parsers/ooxml/__init__.py
benker/parsers/ooxml/namespaces.py
benker/parsers/ooxml/types.py
benker/parsers/ooxml/w_pg_sz.py
benker/parsers/ooxml/w_shd.py
benker/schemas/__init__.py
benker/schemas/cals.xsd
benker/schemas/calstblx.xsd
tests/builders/__init__.py
tests/builders/test_base_builder.py
tests/builders/test_cals_builder.py
tests/builders/test_formex_builder.py
tests/common/__init__.py
tests/common/test_lxml_Iterwalk.py
tests/common/test_lxml_qname.py
tests/converters/__init__.py
tests/converters/cals_comparator.py
tests/converters/test_convert_cals2formex.py
tests/converters/test_convert_formex2cals.py
tests/converters/test_convert_ooxml2cals.py
tests/converters/test_convert_ooxml2formex4.py
tests/parsers/__init__.py
tests/parsers/test_formex_parser.py
tests/parsers/test_ooxml_parser.py
tests/parsers/cals/__init__.py
tests/parsers/cals/test_cals_parser.py
tests/parsers/cals/test_frame_styles.py
tests/resources/__init__.py
tests/resources/cals/README.md
tests/resources/cals/fix_10_embed_gr_notes1.xml
tests/resources/cals/fix_10_embed_gr_notes2.xml
tests/resources/cals/fix_11_corpus_width_missing.xml
tests/resources/cals/fix_12_missing_colspec_attributes.xml
tests/resources/cals/fix_9_lost_text_in_entries.xml
Benker-0.5.4.dist-info/LICENSE
Benker-0.5.4.dist-info/METADATA
Benker-0.5.4.dist-info/WHEEL
Benker-0.5.4.dist-info/top_level.txt
Benker-0.5.4.dist-info/zip-safe
Benker-0.5.4.dist-info/RECORD
