Metadata-Version: 2.1
Name: Benker
Version: 0.5.4
Summary: Easily convert your CALS, HTML, Formex4, Office Open XML (docx) tables from one format to another.
Home-page: https://github.com/laurent-laporte-pro/benker
Author: Laurent LAPORTE
Author-email: laurent.laporte.pro@gmail.com
License: MIT
Project-URL: Documentation, https://benker.readthedocs.io
Project-URL: Source Code, https://github.com/laurent-laporte-pro/benker
Project-URL: Issue tracker, https://github.com/laurent-laporte-pro/benker/issues
Keywords: Office,Word,Excel,PowerPoint,docx,xlsx,pptx,CALS,HTML,Formex,table,converter,conversion
Platform: posix
Platform: nt
Classifier: Development Status :: 5 - Production/Stable
Classifier: License :: OSI Approved :: MIT License
Classifier: Programming Language :: Python
Classifier: Programming Language :: Python :: 2
Classifier: Programming Language :: Python :: 2.7
Classifier: Programming Language :: Python :: 3
Classifier: Programming Language :: Python :: 3.5
Classifier: Programming Language :: Python :: 3.6
Classifier: Programming Language :: Python :: 3.7
Classifier: Programming Language :: Python :: 3.8
Classifier: Programming Language :: Python :: 3.9
Classifier: Programming Language :: Python :: 3.10
Classifier: Topic :: Text Processing
Classifier: Topic :: Text Processing :: Markup
Classifier: Topic :: Text Processing :: Markup :: HTML
Classifier: Topic :: Text Processing :: Markup :: XML
Classifier: Intended Audience :: Information Technology
Classifier: Intended Audience :: Manufacturing
Classifier: Topic :: Printing
Classifier: Operating System :: MacOS
Classifier: Operating System :: Microsoft
Classifier: Operating System :: Microsoft :: Windows
Classifier: Operating System :: POSIX
Classifier: Operating System :: POSIX :: Other
Classifier: Operating System :: Unix
Requires-Python: >=2.7, !=3.0.*, !=3.1.*, !=3.2.*, !=3.3.*
License-File: LICENSE
Requires-Dist: lxml
Provides-Extra: dev
Requires-Dist: Tox ; extra == 'dev'
Requires-Dist: isort ; extra == 'dev'
Requires-Dist: check-manifest ; extra == 'dev'
Provides-Extra: test
Requires-Dist: xmldiff ; extra == 'test'
Requires-Dist: PyTest (<5) ; (python_version < "3") and extra == 'test'
Requires-Dist: PyTest-Cov (<2.6) ; (python_version < "3") and extra == 'test'
Requires-Dist: PyTest ; (python_version >= "3.6") and extra == 'test'
Requires-Dist: PyTest-Cov ; (python_version >= "3.6") and extra == 'test'
